caprover_api/__init__.py
caprover_api/caprover_api.py
caprover_api-0.1.24.dist-info/AUTHORS.rst
caprover_api-0.1.24.dist-info/LICENSE
caprover_api-0.1.24.dist-info/METADATA
caprover_api-0.1.24.dist-info/WHEEL
caprover_api-0.1.24.dist-info/top_level.txt
caprover_api-0.1.24.dist-info/RECORD
