Metadata-Version: 2.2
Name: caprover_api
Version: 0.1.24
Summary: unofficial caprover api to deploy apps to caprover
Home-page: https://github.com/ak4zh/caprover-api
Author: Akash Agarwal
Author-email: agwl.akash@gmail.com
License: MIT license
Keywords: caprover_api
Classifier: Development Status :: 2 - Pre-Alpha
Classifier: Intended Audience :: Developers
Classifier: License :: OSI Approved :: MIT License
Classifier: Natural Language :: English
Classifier: Programming Language :: Python :: 3
Classifier: Programming Language :: Python :: 3.6
Classifier: Programming Language :: Python :: 3.7
Classifier: Programming Language :: Python :: 3.8
Requires-Python: >=3.6
License-File: LICENSE
License-File: AUTHORS.rst
Requires-Dist: requests>=2.25.1
Requires-Dist: PyYAML>=5.4.1
Dynamic: author
Dynamic: author-email
Dynamic: classifier
Dynamic: description
Dynamic: home-page
Dynamic: keywords
Dynamic: license
Dynamic: requires-dist
Dynamic: requires-python
Dynamic: summary
